py_secretserver/__init__.py
py_secretserver/ss_session.py
py_secretserver-0.0.5.dist-info/LICENSE
py_secretserver-0.0.5.dist-info/METADATA
py_secretserver-0.0.5.dist-info/WHEEL
py_secretserver-0.0.5.dist-info/top_level.txt
py_secretserver-0.0.5.dist-info/RECORD
