Metadata-Version: 2.1
Name: py-secretserver
Version: 0.0.5
Summary: Package to interact and automate against Secret Server REST API
Home-page: https://github.com/thycotic-ps/py-secretserver
Author: Shawn Melton
Author-email: shawn.melton@thycotic.com
License: UNKNOWN
Project-URL: Documentation, https://github.com/thycotic-ps/py-secretserver
Project-URL: Bug Reports, https://github.com/thycotic-ps/py-secretserver/issues
Project-URL: Source Code, https://github.com/thycotic-ps/py-secretserver
Keywords: secretserver,restapi,automate,security,secret,secrets,vault
Platform: UNKNOWN
Classifier: Development Status :: 5 - Production/Stable
Classifier: Intended Audience :: Developers
Classifier: Topic :: Software Development :: Build Tools
Classifier: Programming Language :: Python :: 3.6
Classifier: Programming Language :: Python :: 3.7
Classifier: Programming Language :: Python :: 3.8
Classifier: Programming Language :: Python :: 3.9
Classifier: License :: OSI Approved :: Apache Software License
Classifier: Operating System :: OS Independent
Requires-Python: >=3.6
Provides-Extra: dev
Requires-Dist: check-manifest ; extra == 'dev'
